Workbook

Sheet 365RE
B1: 365 DataScience RE California Database
B2: Practical example
B4: Product | L4: Customer
B5: ID | C5: Building | D5: Year of sale | E5: Month of sale | F5: Type of property | G5: Property # | H5: Area (ft.) | I5: Price | J5: Status | L5: Customer ID | M5: Entity | N5: Name | O5: Surname | P5: Age at time of purchase | Q5: Interval | R5: Y | S5: M | T5: D | U5: Gender | V5: Country | W5: State | X5: Purpose | Y5: Deal satisfaction | Z5: Mortgage | AA5: Source
B6: =C6*1000+G6 -> 1030 | C6: 1 | D6: 2005 | E6: 11 | F6: Apartment | G6: 30 | H6: 743.0856 | I6: 246172.68 | J6: Sold | L6: C0028 | M6: Individual | N6: Madalyn | O6: Mercer | P6: =D6-R6 -> 19 | Q6: =IF(P6<26,"18-25",IF(P6<36,"26-35",IF(P6<46,"36-45",IF(P6<56,"46-55",IF(P6<66,"56-65","65+"))))) -> 18-25 | R6: 1986 | S6: 6 | T6: 21 | U6: F | V6: USA | W6: California | X6: Home | Y6: 5 | Z6: No | AA6: Website
B7: =C7*1000+G7 -> 1029 | C7: 1 | D7: 2005 | E7: 10 | F7: Apartment | G7: 29 | H7: 756.2128 | I7: 246331.9 | J7: Sold | L7: C0027 | M7: Individual | N7: Lara | O7: Carrillo | P7: =IF((D7-R7)=0," ",D7-R7) -> 22 | Q7: =IF(P7<26,"18-25",IF(P7<36,"26-35",IF(P7<46,"36-45",IF(P7<56,"46-55",IF(P7<66,"56-65","65+"))))) -> 18-25 | R7: 1983 | S7: 2 | T7: 24 | U7: F | V7: USA | W7: California | X7: Home | Y7: 5 | Z7: No | AA7: Website
B8: =C8*1000+G8 -> 2002 | C8: 2 | D8: 2007 | E8: 7 | F8: Apartment | G8: 2 | H8: 587.2808 | I8: 209280.91 | J8: Sold | L8: C0112 | M8: Individual | N8: Donavan | O8: Flowers | P8: =IF((D8-R8)=0," ",D8-R8) -> 22 | Q8: =IF(P8<26,"18-25",IF(P8<36,"26-35",IF(P8<46,"36-45",IF(P8<56,"46-55",IF(P8<66,"56-65","65+"))))) -> 18-25 | R8: 1985 | S8: 12 | T8: 27 | U8: M | V8: USA | W8: California | X8: Home | Y8: 1 | Z8: Yes | AA8: Client
B9: =C9*1000+G9 -> 2031 | C9: 2 | D9: 2007 | E9: 12 | F9: Apartment | G9: 31 | H9: 1604.7464 | I9: 452667.01 | J9: Sold | L9: C0160 | M9: Individual | N9: Darien | O9: Dorsey | P9: =IF((D9-R9)=0," ",D9-R9) -> 22 | Q9: =IF(P9<26,"18-25",IF(P9<36,"26-35",IF(P9<46,"36-45",IF(P9<56,"46-55",IF(P9<66,"56-65","65+"))))) -> 18-25 | R9: 1985 | S9: 12 | T9: 27 | U9: M | V9: USA | W9: California | X9: Investment | Y9: 3 | Z9: Yes | AA9: Website
B10: =C10*1000+G10 -> 1049 | C10: 1 | D10: 2004 | E10: 11 | F10: Apartment | G10: 49 | H10: 1375.4508 | I10: 467083.31 | J10: Sold | L10: C0014 | M10: Individual | N10: Alessandra | O10: Perry | P10: =IF((D10-R10)=0," ",D10-R10) -> 25 | Q10: =IF(P10<26,"18-25",IF(P10<36,"26-35",IF(P10<46,"36-45",IF(P10<56,"46-55",IF(P10<66,"56-65","65+"))))) -> 18-25 | R10: 1979 | S10: 5 | T10: 15 | U10: F | V10: USA | W10: California | X10: Home | Y10: 4 | Z10: No | AA10: Agency
B11: =C11*1000+G11 -> 3011 | C11: 3 | D11: 2007 | E11: 9 | F11: Apartment | G11: 11 | H11: 675.19 | I11: 203491.85 | J11: Sold | L11: C0125 | M11: Individual | N11: Kaitlin | O11: Owen | P11: =IF((D11-R11)=0," ",D11-R11) -> 26 | Q11: =IF(P11<26,"18-25",IF(P11<36,"26-35",IF(P11<46,"36-45",IF(P11<56,"46-55",IF(P11<66,"56-65","65+"))))) -> 26-35 | R11: 1981 | S11: 12 | T11: 26 | U11: F | V11: USA | W11: Virginia | X11: Investment | Y11: 5 | Z11: No | AA11: Client
B12: =C12*1000+G12 -> 3026 | C12: 3 | D12: 2007 | E12: 9 | F12: Apartment | G12: 26 | H12: 670.886 | I12: 212520.83 | J12: Sold | L12: C0125 | M12: Individual | N12: Kaitlin | O12: Owen | P12: =IF((D12-R12)=0," ",D12-R12) -> 26 | Q12: =IF(P12<26,"18-25",IF(P12<36,"26-35",IF(P12<46,"36-45",IF(P12<56,"46-55",IF(P12<66,"56-65","65+"))))) -> 26-35 | R12: 1981 | S12: 12 | T12: 26 | U12: F | V12: USA | W12: Virginia | X12: Investment | Y12: 5 | Z12: No | AA12: Agency
B13: =C13*1000+G13 -> 3023 | C13: 3 | D13: 2008 | E13: 1 | F13: Apartment | G13: 23 | H13: 720.8124 | I13: 198591.85 | J13: Sold | L13: C0166 | M13: Individual | N13: Terry | O13: Forbes | P13: =IF((D13-R13)=0," ",D13-R13) -> 26 | Q13: =IF(P13<26,"18-25",IF(P13<36,"26-35",IF(P13<46,"36-45",IF(P13<56,"46-55",IF(P13<66,"56-65","65+"))))) -> 26-35 | R13: 1982 | S13: 5 | T13: 27 | U13: M | V13: USA | W13: California | X13: Home | Y13: 5 | Z13: No | AA13: Client
B14: =C14*1000+G14 -> 1031 | C14: 1 | D14: 2006 | E14: 6 | F14: Apartment | G14: 31 | H14: 782.252 | I14: 265467.68 | J14: Sold | L14: C0034 | M14: Individual | N14: Kole | O14: Shannon | P14: =IF((D14-R14)=0," ",D14-R14) -> 27 | Q14: =IF(P14<26,"18-25",IF(P14<36,"26-35",IF(P14<46,"36-45",IF(P14<56,"46-55",IF(P14<66,"56-65","65+"))))) -> 26-35 | R14: 1979 | S14: 6 | T14: 27 | U14: M | V14: USA | W14: Arizona | X14: Home | Y14: 2 | Z14: Yes | AA14: Website
B15: =C15*1000+G15 -> 4023 | C15: 4 | D15: 2006 | E15: 3 | F15: Apartment | G15: 23 | H15: 794.5184 | I15: 235633.26 | J15: Sold | L15: C0170 | M15: Individual | N15: Emmy | O15: Singh | P15: =IF((D15-R15)=0," ",D15-R15) -> 27 | Q15: =IF(P15<26,"18-25",IF(P15<36,"26-35",IF(P15<46,"36-45",IF(P15<56,"46-55",IF(P15<66,"56-65","65+"))))) -> 26-35 | R15: 1979 | S15: 12 | T15: 3 | U15: F | V15: USA | W15: Virginia | X15: Investment | Y15: 3 | Z15: Yes | AA15: Agency
B16: =C16*1000+G16 -> 1036 | C16: 1 | D16: 2004 | E16: 10 | F16: Apartment | G16: 36 | H16: 1160.3584 | I16: 317473.86 | J16: Sold | L16: C0009 | M16: Individual | N16: Arabella | O16: Ferrell | P16: =IF((D16-R16)=0," ",D16-R16) -> 28 | Q16: =IF(P16<26,"18-25",IF(P16<36,"26-35",IF(P16<46,"36-45",IF(P16<56,"46-55",IF(P16<66,"56-65","65+"))))) -> 26-35 | R16: 1976 | S16: 8 | T16: 17 | U16: F | V16: USA | W16: Oregon | X16: Home | Y16: 1 | Z16: No | AA16: Agency
B17: =C17*1000+G17 -> 1046 | C17: 1 | D17: 2006 | E17: 8 | F17: Apartment | G17: 46 | H17: 1942.5028 | I17: 503790.23 | J17: Sold | L17: C0041 | M17: Individual | N17: Christian | O17: Costa | P17: =IF((D17-R17)=0," ",D17-R17) -> 26 | Q17: =IF(P17<26,"18-25",IF(P17<36,"26-35",IF(P17<46,"36-45",IF(P17<56,"46-55",IF(P17<66,"56-65","65+"))))) -> 26-35 | R17: 1980 | S17: 9 | T17: 14 | U17: M | V17: USA | W17: California | X17: Home | Y17: 5 | Z17: No | AA17: Website
B18: =C18*1000+G18 -> 4035 | C18: 4 | D18: 2007 | E18: 10 | F18: Apartment | G18: 35 | H18: 794.5184 | I18: 217786.38 | J18: Sold | L18: C0057 | M18: Individual | N18: Michelle | O18: Cameron | P18: =IF((D18-R18)=0," ",D18-R18) -> 29 | Q18: =IF(P18<26,"18-25",IF(P18<36,"26-35",IF(P18<46,"36-45",IF(P18<56,"46-55",IF(P18<66,"56-65","65+"))))) -> 26-35 | R18: 1978 | S18: 6 | T18: 4 | U18: F | V18: USA | W18: Nevada | X18: Home | Y18: 3 | Z18: Yes | AA18: Website
... B46: =C46*1000+G46 -> 4005 | C46: 4 | D46: 2007 | E46: 11 | F46: Apartment | G46: 5 | H46: 1121.9452 | I46: 344530.89 | J46: Sold | L46: C0142 | M46: Individual | N46: Kassidy | O46: Vega | P46: =IF((D46-R46)=0," ",D46-R46) -> 35 | Q46: =IF(P46<26,"18-25",IF(P46<36,"26-35",IF(P46<46,"36-45",IF(P46<56,"46-55",IF(P46<66,"56-65","65+"))))) -> 26-35 | R46: 1972 | S46: 5 | T46: 7 | U46: F | V46: USA | W46: California | X46: Home | Y46: 5 | Z46: No | AA46: Website
B47: =C47*1000+G47 -> 1032 | C47: 1 | D47: 2005 | E47: 1 | F47: Apartment | G47: 32 | H47: 782.252 | I47: 215410.28 | J47: Sold | L47: C0015 | M47: Individual | N47: Lauryn | O47: Patrick | P47: =IF((D47-R47)=0," ",D47-R47) -> 36 | Q47: =IF(P47<26,"18-25",IF(P47<36,"26-35",IF(P47<46,"36-45",IF(P47<56,"46-55",IF(P47<66,"56-65","65+"))))) -> 36-45 | R47: 1969 | S47: 10 | T47: 30 | U47: F | V47: Belgium | X47: Home | Y47: 2 | Z47: No | AA47: Agency
B48: =C48*1000+G48 -> 3046 | C48: 3 | D48: 2007 | E48: 8 | F48: Apartment | G48: 46 | H48: 923.208 | I48: 252185.99 | J48: Sold | L48: C0122 | M48: Individual | N48: Brock | O48: Fischer | P48: =IF((D48-R48)=0," ",D48-R48) -> 36 | Q48: =IF(P48<26,"18-25",IF(P48<36,"26-35",IF(P48<46,"36-45",IF(P48<56,"46-55",IF(P48<66,"56-65","65+"))))) -> 36-45 | R48: 1971 | S48: 5 | T48: 29 | U48: M | V48: USA | W48: Kansas | X48: Home | Y48: 3 | Z48: No | AA48: Website
B49: =C49*1000+G49 -> 1041 | C49: 1 | D49: 2005 | E49: 3 | F49: Apartment | G49: 41 | H49: 1434.0928 | I49: 480545.81 | J49: Sold | L49: C0017 | M49: Individual | N49: Memphis | O49: Mcconnell | P49: =IF((D49-R49)=0," ",D49-R49) -> 37 | Q49: =IF(P49<26,"18-25",IF(P49<36,"26-35",IF(P49<46,"36-45",IF(P49<56,"46-55",IF(P49<66,"56-65","65+"))))) -> 36-45 | R49: 1968 | S49: 8 | T49: 25 | U49: M | V49: USA | W49: California | X49: Home | Y49: 2 | Z49: Yes | AA49: Website
B50: =C50*1000+G50 -> 1012 | C50: 1 | D50: 2005 | E50: 3 | F50: Apartment | G50: 12 | H50: 1160.3584 | I50: 300385.62 | J50: Sold | L50: C0020 | M50: Individual | N50: Grant | O50: Weber | P50: =IF((D50-R50)=0," ",D50-R50) -> 37 | Q50: =IF(P50<26,"18-25",IF(P50<36,"26-35",IF(P50<46,"36-45",IF(P50<56,"46-55",IF(P50<66,"56-65","65+"))))) -> 36-45 | R50: 1968 | S50: 9 | T50: 8 | U50: M | V50: USA | W50: California | X50: Home | Y50: 5 | Z50: Yes | AA50: Website
A51: x | B51: =C51*1000+G51 -> 5033 | C51: 5 | D51: 2008 | E51: 5 | F51: Apartment | G51: 33 | H51: 798.2844 | I51: 240539.35 | J51: Sold | L51: C0086 | M51: Individual | N51: Jace | O51: Riggs | P51: =IF((D51-R51)=0," ",D51-R51) -> 37 | Q51: =IF(P51<26,"18-25",IF(P51<36,"26-35",IF(P51<46,"36-45",IF(P51<56,"46-55",IF(P51<66,"56-65","65+"))))) -> 36-45 | R51: 1971 | S51: 8 | T51: 20 | U51: F | V51: USA | W51: California | X51: Home | Y51: 1 | Z51: No | AA51: Website
B52: =C52*1000+G52 -> 4006 | C52: 4 | D52: 2006 | E52: 7 | F52: Apartment | G52: 6 | H52: 733.1864 | I52: 222138.72 | J52: Sold | L52: C0150 | M52: Individual | N52: Emmett | O52: Estes | P52: =IF((D52-R52)=0," ",D52-R52) -> 37 | Q52: =IF(P52<26,"18-25",IF(P52<36,"26-35",IF(P52<46,"36-45",IF(P52<56,"46-55",IF(P52<66,"56-65","65+"))))) -> 36-45 | R52: 1969 | S52: 6 | T52: 5 | U52: M | V52: USA | W52: California | X52: Home | Y52: 3 | Z52: No | AA52: Website
B53: =C53*1000+G53 -> 5040 | C53: 5 | D53: 2007 | E53: 12 | F53: Apartment | G53: 40 | H53: 798.2844 | I53: 228410.05 | J53: Sold | L53: C0156 | M53: Individual | N53: Isis | O53: Rios | P53: =IF((D53-R53)=0," ",D53-R53) -> 37 | Q53: =IF(P53<26,"18-25",IF(P53<36,"26-35",IF(P53<46,"36-45",IF(P53<56,"46-55",IF(P53<66,"56-65","65+"))))) -> 36-45 | R53: 1970 | S53: 4 | T53: 1 | U53: M | V53: USA | W53: California | X53: Investment | Y53: 4 | Z53: No | AA53: Website
B54: =C54*1000+G54 -> 4013 | C54: 4 | D54: 2007 | E54: 1 | F54: Apartment | G54: 13 | H54: 733.1864 | I54: 197053.51 | J54: Sold | L54: C0169 | M54: Individual | N54: Mason | O54: Gilbert | P54: =IF((D54-R54)=0," ",D54-R54) -> 37 | Q54: =IF(P54<26,"18-25",IF(P54<36,"26-35",IF(P54<46,"36-45",IF(P54<56,"46-55",IF(P54<66,"56-65","65+"))))) -> 36-45 | R54: 1970 | S54: 7 | T54: 31 | U54: M | V54: USA | W54: Colorado | X54: Home | Y54: 2 | Z54: No | AA54: Agency
B55: =C55*1000+G55 -> 1003 | C55: 1 | D55: 2005 | E55: 6 | F55: Office | G55: 3 | H55: 717.0464 | I55: 193660.62 | J55: Sold | L55: C0022 | M55: Individual | N55: Zain | O55: Horne | P55: =IF((D55-R55)=0," ",D55-R55) -> 38 | Q55: =IF(P55<26,"18-25",IF(P55<36,"26-35",IF(P55<46,"36-45",IF(P55<56,"46-55",IF(P55<66,"56-65","65+"))))) -> 36-45 | R55: 1967 | S55: 4 | T55: 13 | U55: M | V55: USA | W55: Arizona | X55: Home | Y55: 1 | Z55: Yes | AA55: Website
B56: =C56*1000+G56 -> 2009 | C56: 2 | D56: 2007 | E56: 3 | F56: Apartment | G56: 9 | H56: 747.4972 | I56: 237060.15 | J56: Sold | L56: C0072 | M56: Individual | N56: Dayton | O56: Hatfield | P56: =IF((D56-R56)=0," ",D56-R56) -> 38 | Q56: =IF(P56<26,"18-25",IF(P56<36,"26-35",IF(P56<46,"36-45",IF(P56<56,"46-55",IF(P56<66,"56-65","65+"))))) -> 36-45 | R56: 1969 | S56: 4 | T56: 19 | U56: M | V56: USA | W56: Colorado | X56: Investment | Y56: 4 | Z56: Yes | AA56: Agency
B57: =C57*1000+G57 -> 4024 | C57: 4 | D57: 2007 | E57: 11 | F57: Apartment | G57: 24 | H57: 1121.9452 | I57: 372001.7 | J57: Sold | L57: C0136 | M57: Individual | N57: Annabel | O57: Robles | P57: =IF((D57-R57)=0," ",D57-R57) -> 38 | Q57: =IF(P57<26,"18-25",IF(P57<36,"26-35",IF(P57<46,"36-45",IF(P57<56,"46-55",IF(P57<66,"56-65","65+"))))) -> 36-45 | R57: 1969 | S57: 10 | T57: 14 | U57: F | V57: USA | W57: California | X57: Home | Y57: 5 | Z57: Yes | AA57: Website
B58: =C58*1000+G58 -> 4012 | C58: 4 | D58: 2007 | E58: 11 | F58: Apartment | G58: 12 | H58: 1121.9452 | I58: 290031.26 | J58: Sold | L58: C0149 | M58: Individual | N58: Kayden | O58: Olsen | P58: =IF((D58-R58)=0," ",D58-R58) -> 38 | Q58: =IF(P58<26,"18-25",IF(P58<36,"26-35",IF(P58<46,"36-45",IF(P58<56,"46-55",IF(P58<66,"56-65","65+"))))) -> 36-45 | R58: 1969 | S58: 10 | T58: 17 | U58: F | V58: USA | W58: California | X58: Home | Y58: 5 | Z58: No | AA58: Website
B59: =C59*1000+G59 -> 1035 | C59: 1 | D59: 2004 | E59: 10 | F59: Apartment | G59: 35 | H59: 827.8744 | I59: 238811.06 | J59: Sold | L59: C0011 | M59: Individual | N59: Davion | O59: Stout | P59: =IF((D59-R59)=0," ",D59-R59) -> 39 | Q59: =IF(P59<26,"18-25",IF(P59<36,"26-35",IF(P59<46,"36-45",IF(P59<56,"46-55",IF(P59<66,"56-65","65+"))))) -> 36-45 | R59: 1965 | S59: 7 | T59: 20 | U59: M | V59: USA | W59: Nevada | X59: Home | Y59: 1 | Z59: Yes | AA59: Agency
B60: =C60*1000+G60 -> 2017 | C60: 2 | D60: 2007 | E60: 3 | F60: Apartment | G60: 17 | H60: 747.4972 | I60: 199054.2 | J60: Sold | L60: C0073 | M60: Individual | N60: Kevin | O60: Mata | P60: =IF((D60-R60)=0," ",D60-R60) -> 39 | Q60: =IF(P60<26,"18-25",IF(P60<36,"26-35",IF(P60<46,"36-45",IF(P60<56,"46-55",IF(P60<66,"56-65","65+"))))) -> 36-45 | R60: 1968 | S60: 10 | T60: 12 | U60: M | V60: USA | W60: Colorado | X60: Investment | Y60: 2 | Z60: No | AA60: Agency
B61: =C61*1000+G61 -> 4051 | C61: 4 | D61: 2007 | E61: 3 | F61: Apartment | G61: 51 | H61: 1608.8352 | I61: 496266.41 | J61: Sold | L61: C0110 | M61: Individual | N61: Kareem | O61: Liu | P61: =IF((D61-R61)=0," ",D61-R61) -> 39 | Q61: =IF(P61<26,"18-25",IF(P61<36,"26-35",IF(P61<46,"36-45",IF(P61<56,"46-55",IF(P61<66,"56-65","65+"))))) -> 36-45 | R61: 1968 | S61: 5 | T61: 11 | U61: F | V61: USA | W61: California | X61: Home | Y61: 4 | Z61: Yes | AA61: Website
B62: =C62*1000+G62 -> 3014 | C62: 3 | D62: 2007 | E62: 7 | F62: Apartment | G62: 14 | H62: 1132.0596 | I62: 346906.89 | J62: Sold | L62: C0111 | M62: Individual | N62: Grace | O62: Stein | P62: =IF((D62-R62)=0," ",D62-R62) -> 39 | Q62: =IF(P62<26,"18-25",IF(P62<36,"26-35",IF(P62<46,"36-45",IF(P62<56,"46-55",IF(P62<66,"56-65","65+"))))) -> 36-45 | R62: 1968 | S62: 12 | T62: 20 | U62: F | V62: USA | W62: California | X62: Home | Y62: 3 | Z62: Yes | AA62: Website
B63: =C63*1000+G63 -> 2051 | C63: 2 | D63: 2007 | E63: 9 | F63: Apartment | G63: 51 | H63: 1383.8436 | I63: 376964.62 | J63: Sold | L63: C0123 | M63: Individual | N63: Lydia | O63: Tate | P63: =IF((D63-R63)=0," ",D63-R63) -> 39 | Q63: =IF(P63<26,"18-25",IF(P63<36,"26-35",IF(P63<46,"36-45",IF(P63<56,"46-55",IF(P63<66,"56-65","65+"))))) -> 36-45 | R63: 1968 | S63: 8 | T63: 14 | U63: F | V63: USA | W63: California | X63: Home | Y63: 3 | Z63: Yes | AA63: Website
B64: =C64*1000+G64 -> 2025 | C64: 2 | D64: 2007 | E64: 2 | F64: Apartment | G64: 25 | H64: 927.8348 | I64: 315733.15 | J64: Sold | L64: C0070 | M64: Individual | N64: Aleksandra | O64: Karenina | P64: =IF((D64-R64)=0," ",D64-R64) -> 40 | Q64: =IF(P64<26,"18-25",IF(P64<36,"26-35",IF(P64<46,"36-45",IF(P64<56,"46-55",IF(P64<66,"56-65","65+"))))) -> 36-45 | R64: 1967 | S64: 6 | T64: 13 | U64: F | V64: Russia | X64: Home | Y64: 1 | Z64: No | AA64: Agency
B65: =C65*1000+G65 -> 3047 | C65: 3 | D65: 2007 | E65: 3 | F65: Apartment | G65: 47 | H65: 669.1644 | I65: 188273.73 | J65: Sold | L65: C0075 | M65: Individual | N65: Sincere | O65: Hansen | P65: =IF((D65-R65)=0," ",D65-R65) -> 40 | Q65: =IF(P65<26,"18-25",IF(P65<36,"26-35",IF(P65<46,"36-45",IF(P65<56,"46-55",IF(P65<66,"56-65","65+"))))) -> 36-45 | R65: 1967 | S65: 1 | T65: 19 | U65: F | V65: USA | W65: California | X65: Investment | Y65: 2 | Z65: Yes | AA65: Agency
B66: =C66*1000+G66 -> 2046 | C66: 2 | D66: 2007 | E66: 3 | F66: Apartment | G66: 46 | H66: 928.1576 | I66: 253831.02 | J66: Sold | L66: C0076 | M66: Individual | N66: Luke | O66: Lynn | P66: =IF((D66-R66)=0," ",D66-R66) -> 40 | Q66: =IF(P66<26,"18-25",IF(P66<36,"26-35",IF(P66<46,"36-45",IF(P66<56,"46-55",IF(P66<66,"56-65","65+"))))) -> 36-45 | R66: 1967 | S66: 2 | T66: 7 | U66: M | V66: USA | W66: California | X66: Home | Y66: 2 | Z66: Yes | AA66: Agency
B67: =C67*1000+G67 -> 5016 | C67: 5 | D67: 2007 | E67: 6 | F67: Apartment | G67: 16 | H67: 798.4996 | I67: 278575.87 | J67: Sold | L67: C0105 | M67: Individual | N67: Myla | O67: Ewing | P67: =IF((D67-R67)=0," ",D67-R67) -> 40 | Q67: =IF(P67<26,"18-25",IF(P67<36,"26-35",IF(P67<46,"36-45",IF(P67<56,"46-55",IF(P67<66,"56-65","65+"))))) -> 36-45 | R67: 1967 | S67: 2 | T67: 3 | U67: F | V67: USA | W67: Oregon | X67: Investment | Y67: 2 | Z67: No | AA67: Client
B68: =C68*1000+G68 -> 4041 | C68: 4 | D68: 2007 | E68: 10 | F68: Apartment | G68: 41 | H68: 1305.6184 | I68: 402081.8 | J68: Sold | L68: C0135 | M68: Individual | N68: Morgan | O68: Glass | P68: =IF((D68-R68)=0," ",D68-R68) -> 40 | Q68: =IF(P68<26,"18-25",IF(P68<36,"26-35",IF(P68<46,"36-45",IF(P68<56,"46-55",IF(P68<66,"56-65","65+"))))) -> 36-45 | R68: 1967 | S68: 5 | T68: 12 | U68: M | V68: USA | W68: Utah | X68: Home | Y68: 5 | Z68: No | AA68: Agency
B69: =C69*1000+G69 -> 4018 | C69: 4 | D69: 2007 | E69: 11 | F69: Apartment | G69: 18 | H69: 1121.9452 | I69: 310832.59 | J69: Sold | L69: C0153 | M69: Individual | N69: Camille | O69: Sharp | P69: =IF((D69-R69)=0," ",D69-R69) -> 40 | Q69: =IF(P69<26,"18-25",IF(P69<36,"26-35",IF(P69<46,"36-45",IF(P69<56,"46-55",IF(P69<66,"56-65","65+"))))) -> 36-45 | R69: 1967 | S69: 10 | T69: 17 | U69: F | V69: USA | W69: California | X69: Home | Y69: 5 | Z69: No | AA69: Website
B70: =C70*1000+G70 -> 2005 | C70: 2 | D70: 2006 | E70: 9 | F70: Apartment | G70: 5 | H70: 785.48 | I70: 257183.48 | J70: Sold | L70: C0047 | M70: Individual | N70: Alejandra | O70: Greer | P70: =IF((D70-R70)=0," ",D70-R70) -> 41 | Q70: =IF(P70<26,"18-25",IF(P70<36,"26-35",IF(P70<46,"36-45",IF(P70<56,"46-55",IF(P70<66,"56-65","65+"))))) -> 36-45 | R70: 1965 | S70: 1 | T70: 11 | U70: F | V70: Denmark | X70: Investment | Y70: 1 | Z70: No | AA70: Agency
B71: =C71*1000+G71 -> 2010 | C71: 2 | D71: 2006 | E71: 11 | F71: Apartment | G71: 10 | H71: 927.0816 | I71: 326885.34 | J71: Sold | L71: C0060 | M71: Individual | N71: Valentina | O71: Simpson | P71: =IF((D71-R71)=0," ",D71-R71) -> 41 | Q71: =IF(P71<26,"18-25",IF(P71<36,"26-35",IF(P71<46,"36-45",IF(P71<56,"46-55",IF(P71<66,"56-65","65+"))))) -> 36-45 | R71: 1965 | S71: 1 | T71: 24 | U71: F | V71: USA | W71: California | X71: Home | Y71: 4 | Z71: Yes | AA71: Agency
B72: =C72*1000+G72 -> 2022 | C72: 2 | D72: 2007 | E72: 1 | F72: Apartment | G72: 22 | H72: 1109.2484 | I72: 344568.74 | J72: Sold | L72: C0066 | M72: Individual | N72: Helen | O72: Williamson | P72: =IF((D72-R72)=0," ",D72-R72) -> 41 | Q72: =IF(P72<26,"18-25",IF(P72<36,"26-35",IF(P72<46,"36-45",IF(P72<56,"46-55",IF(P72<66,"56-65","65+"))))) -> 36-45 | R72: 1966 | S72: 2 | T72: 26 | U72: F | V72: USA | W72: Colorado | X72: Home | Y72: 5 | Z72: Yes | AA72: Agency
B73: =C73*1000+G73 -> 2047 | C73: 2 | D73: 2007 | E73: 2 | F73: Apartment | G73: 47 | H73: 649.7964 | I73: 214631.68 | J73: Sold | L73: C0068 | M73: Individual | N73: Nicolas | O73: Navarro | P73: =IF((D73-R73)=0," ",D73-R73) -> 41 | Q73: =IF(P73<26,"18-25",IF(P73<36,"26-35",IF(P73<46,"36-45",IF(P73<56,"46-55",IF(P73<66,"56-65","65+"))))) -> 36-45 | R73: 1966 | S73: 6 | T73: 17 | U73: M | V73: USA | W73: Oregon | X73: Investment | Y73: 3 | Z73: No | AA73: Agency
B74: =C74*1000+G74 -> 2012 | C74: 2 | D74: 2007 | E74: 4 | F74: Apartment | G74: 12 | H74: 785.48 | I74: 237207.68 | J74: Sold | L74: C0090 | M74: Individual | N74: Case | O74: Sanchez | P74: =IF((D74-R74)=0," ",D74-R74) -> 41 | Q74: =IF(P74<26,"18-25",IF(P74<36,"26-35",IF(P74<46,"36-45",IF(P74<56,"46-55",IF(P74<66,"56-65","65+"))))) -> 36-45 | R74: 1966 | S74: 5 | T74: 26 | U74: F | V74: USA | W74: California | X74: Home | Y74: 5 | Z74: No | AA74: Website
B75: =C75*1000+G75 -> 3038 | C75: 3 | D75: 2007 | E75: 5 | F75: Apartment | G75: 38 | H75: 1596.3536 | I75: 464549.19 | J75: Sold | L75: C0095 | M75: Individual | N75: Rodrigo | O75: Robinson | P75: =IF((D75-R75)=0," ",D75-R75) -> 41 | Q75: =IF(P75<26,"18-25",IF(P75<36,"26-35",IF(P75<46,"36-45",IF(P75<56,"46-55",IF(P75<66,"56-65","65+"))))) -> 36-45 | R75: 1966 | S75: 8 | T75: 11 | U75: M | V75: USA | W75: California | X75: Home | Y75: 4 | Z75: No | AA75: Website
B76: =C76*1000+G76 -> 4030 | C76: 4 | D76: 2007 | E76: 11 | F76: Apartment | G76: 30 | H76: 1121.9452 | I76: 310577.04 | J76: Sold | L76: C0151 | M76: Individual | N76: Iris | O76: Larsen | P76: =IF((D76-R76)=0," ",D76-R76) -> 41 | Q76: =IF(P76<26,"18-25",IF(P76<36,"26-35",IF(P76<46,"36-45",IF(P76<56,"46-55",IF(P76<66,"56-65","65+"))))) -> 36-45 | R76: 1966 | S76: 9 | T76: 14 | U76: M | V76: USA | W76: California | X76: Home | Y76: 4 | Z76: Yes | AA76: Agency
B77: =C77*1000+G77 -> 3017 | C77: 3 | D77: 2007 | E77: 12 | F77: Apartment | G77: 17 | H77: 743.4084 | I77: 205098.21 | J77: Sold | L77: C0162 | M77: Individual | N77: Araceli | O77: Nelson | P77: =IF((D77-R77)=0," ",D77-R77) -> 41 | Q77: =IF(P77<26,"18-25",IF(P77<36,"26-35",IF(P77<46,"36-45",IF(P77<56,"46-55",IF(P77<66,"56-65","65+"))))) -> 36-45 | R77: 1966 | S77: 9 | T77: 14 | U77: M | V77: Germany | W77: California | X77: Investment | Y77: 5 | Z77: No | AA77: Agency
B78: =C78*1000+G78 -> 1045 | C78: 1 | D78: 2004 | E78: 10 | F78: Apartment | G78: 45 | H78: 756.2128 | I78: 248525.12 | J78: Sold | L78: C0010 | M78: Individual | N78: Trystan | O78: Oconnor | P78: =IF((D78-R78)=0," ",D78-R78) -> 42 | Q78: =IF(P78<26,"18-25",IF(P78<36,"26-35",IF(P78<46,"36-45",IF(P78<56,"46-55",IF(P78<66,"56-65","65+"))))) -> 36-45 | R78: 1962 | S78: 11 | T78: 26 | U78: M | V78: USA | W78: California | X78: Home | Y78: 1 | Z78: No | AA78: Website
B79: =C79*1000+G79 -> 2040 | C79: 2 | D79: 2006 | E79: 10 | F79: Apartment | G79: 40 | H79: 649.7964 | I79: 224463.87 | J79: Sold | L79: C0054 | M79: Individual | N79: Erik | O79: Mora | P79: =IF((D79-R79)=0," ",D79-R79) -> 42 | Q79: =IF(P79<26,"18-25",IF(P79<36,"26-35",IF(P79<46,"36-45",IF(P79<56,"46-55",IF(P79<66,"56-65","65+"))))) -> 36-45 | R79: 1964 | S79: 12 | T79: 7 | U79: M | V79: USA | W79: Oregon | X79: Investment | Y79: 5 | Z79: No | AA79: Agency
B80: =C80*1000+G80 -> 2042 | C80: 2 | D80: 2006 | E80: 11 | F80: Apartment | G80: 42 | H80: 785.48 | I80: 220606.28 | J80: Sold | L80: C0056 | M80: Individual | N80: Emely | O80: Watts | P80: =IF((D80-R80)=0," ",D80-R80) -> 42 | Q80: =IF(P80<26,"18-25",IF(P80<36,"26-35",IF(P80<46,"36-45",IF(P80<56,"46-55",IF(P80<66,"56-65","65+"))))) -> 36-45 | R80: 1964 | S80: 11 | T80: 30 | U80: F | V80: USA | W80: California | X80: Home | Y80: 4 | Z80: No | AA80: Website
B81: =C81*1000+G81 -> 2048 | C81: 2 | D81: 2007 | E81: 3 | F81: Apartment | G81: 48 | H81: 785.48 | I81: 220865 | J81: Sold | L81: C0081 | M81: Individual | N81: Jordyn | O81: Park | P81: =IF((D81-R81)=0," ",D81-R81) -> 42 | Q81: =IF(P81<26,"18-25",IF(P81<36,"26-35",IF(P81<46,"36-45",IF(P81<56,"46-55",IF(P81<66,"56-65","65+"))))) -> 36-45 | R81: 1965 | S81: 4 | T81: 4 | U81: M | V81: USA | W81: Nevada | X81: Investment | Y81: 3 | Z81: Yes | AA81: Website
B82: =C82*1000+G82 -> 3049 | C82: 3 | D82: 2007 | E82: 4 | F82: Apartment | G82: 49 | H82: 1283.4528 | I82: 338181.18 | J82: Sold | L82: C0084 | M82: Individual | N82: Diego | O82: Mendez | P82: =IF((D82-R82)=0," ",D82-R82) -> 42 | Q82: =IF(P82<26,"18-25",IF(P82<36,"26-35",IF(P82<46,"36-45",IF(P82<56,"46-55",IF(P82<66,"56-65","65+"))))) -> 36-45 | R82: 1965 | S82: 5 | T82: 12 | U82: M | V82: Mexico | X82: Home | Y82: 3 | Z82: No | AA82: Agency
B83: =C83*1000+G83 -> 1017 | C83: 1 | D83: 2005 | E83: 2 | F83: Apartment | G83: 17 | H83: 1434.0928 | I83: 432679.91 | J83: Sold | L83: C0016 | M83: Individual | N83: Harley | O83: Lucero | P83: =D83-R83 -> 43 | Q83: =IF(P83<26,"18-25",IF(P83<36,"26-35",IF(P83<46,"36-45",IF(P83<56,"46-55",IF(P83<66,"56-65","65+"))))) -> 36-45 | R83: 1962 | S83: 8 | T83: 10 | U83: M | V83: USA | W83: California | X83: Home | Y83: 1 | Z83: Yes | AA83: Website
B84: =C84*1000+G84 -> 1039 | C84: 1 | D84: 2006 | E84: 6 | F84: Apartment | G84: 39 | H84: 782.252 | I84: 196220.05 | J84: Sold | L84: C0035 | M84: Individual | N84: Emilie | O84: Morrison | P84: =D84-R84 -> 49 | Q84: =IF(P84<26,"18-25",IF(P84<36,"26-35",IF(P84<46,"36-45",IF(P84<56,"46-55",IF(P84<66,"56-65","65+"))))) -> 46-55 | R84: 1957 | S84: 10 | T84: 29 | U84: F | V84: USA | W84: California | X84: Home | Y84: 3 | Z84: Yes | AA84: Website
B85: =C85*1000+G85 -> 2049 | C85: 2 | D85: 2006 | E85: 11 | F85: Apartment | G85: 49 | H85: 1288.6176 | I85: 323915.81 | J85: Sold | L85: C0062 | M85: Individual | N85: Jaylen | O85: Turner | P85: =IF((D85-R85)=0," ",D85-R85) -> 43 | Q85: =IF(P85<26,"18-25",IF(P85<36,"26-35",IF(P85<46,"36-45",IF(P85<56,"46-55",IF(P85<66,"56-65","65+"))))) -> 36-45 | R85: 1963 | S85: 7 | T85: 15 | U85: F | V85: USA | W85: California | X85: Home | Y85: 4 | Z85: No | AA85: Agency
B86: =C86*1000+G86 -> 3054 | C86: 3 | D86: 2007 | E86: 5 | F86: Apartment | G86: 54 | H86: 781.0684 | I86: 200719.02 | J86: Sold | L86: C0099 | M86: Individual | N86: Frank | O86: Meyer | P86: =IF((D86-R86)=0," ",D86-R86) -> 43 | Q86: =IF(P86<26,"18-25",IF(P86<36,"26-35",IF(P86<46,"36-45",IF(P86<56,"46-55",IF(P86<66,"56-65","65+"))))) -> 36-45 | R86: 1964 | S86: 3 | T86: 16 | U86: M | V86: USA | W86: California | X86: Home | Y86: 2 | Z86: No | AA86: Agency
B87: =C87*1000+G87 -> 3055 | C87: 3 | D87: 2007 | E87: 5 | F87: Apartment | G87: 55 | H87: 1222.336 | I87: 380809.52 | J87: Sold | L87: C0099 | M87: Individual | N87: Frank | O87: Meyer | P87: =IF((D87-R87)=0," ",D87-R87) -> 43 | Q87: =IF(P87<26,"18-25",IF(P87<36,"26-35",IF(P87<46,"36-45",IF(P87<56,"46-55",IF(P87<66,"56-65","65+"))))) -> 36-45 | R87: 1964 | S87: 3 | T87: 16 | U87: M | V87: USA | W87: California | X87: Home | Y87: 3 | Z87: Yes | AA87: Agency
B88: =C88*1000+G88 -> 3042 | C88: 3 | D88: 2007 | E88: 7 | F88: Apartment | G88: 42 | H88: 781.0684 | I88: 213942.56 | J88: Sold | L88: C0114 | M88: Individual | N88: Jakobe | O88: Bailey | P88: =IF((D88-R88)=0," ",D88-R88) -> 43 | Q88: =IF(P88<26,"18-25",IF(P88<36,"26-35",IF(P88<46,"36-45",IF(P88<56,"46-55",IF(P88<66,"56-65","65+"))))) -> 36-45 | R88: 1964 | S88: 10 | T88: 6 | U88: M | V88: UK | W88: California | X88: Investment | Y88: 4 | Z88: No | AA88: Agency
B89: =C89*1000+G89 -> 1038 | C89: 1 | D89: 2004 | E89: 8 | F89: Apartment | G89: 38 | H89: 743.0856 | I89: 207581.43 | J89: Sold | L89: C0006 | M89: Individual | N89: Laci | O89: Guerra | P89: =IF((D89-R89)=0," ",D89-R89) -> 48 | Q89: =IF(P89<26,"18-25",IF(P89<36,"26-35",IF(P89<46,"36-45",IF(P89<56,"46-55",IF(P89<66,"56-65","65+"))))) -> 46-55 | R89: 1956 | S89: 6 | T89: 17 | U89: F | V89: USA | W89: California | X89: Home | Y89: 2 | Z89: Yes | AA89: Website
B90: =C90*1000+G90 -> 2020 | C90: 2 | D90: 2006 | E90: 10 | F90: Apartment | G90: 20 | H90: 785.48 | I90: 241671.52 | J90: Sold | L90: C0053 | M90: Individual | N90: Scarlet | O90: Hendricks | P90: =IF((D90-R90)=0," ",D90-R90) -> 44 | Q90: =IF(P90<26,"18-25",IF(P90<36,"26-35",IF(P90<46,"36-45",IF(P90<56,"46-55",IF(P90<66,"56-65","65+"))))) -> 36-45 | R90: 1962 | S90: 1 | T90: 20 | U90: F | V90: USA | W90: California | X90: Home | Y90: 5 | Z90: Yes | AA90: Website
B91: =C91*1000+G91 -> 2014 | C91: 2 | D91: 2007 | E91: 2 | F91: Apartment | G91: 14 | H91: 1109.2484 | I91: 336695.25 | J91: Sold | L91: C0069 | M91: Individual | N91: Alonso | O91: Terrell | P91: =IF((D91-R91)=0," ",D91-R91) -> 44 | Q91: =IF(P91<26,"18-25",IF(P91<36,"26-35",IF(P91<46,"36-45",IF(P91<56,"46-55",IF(P91<66,"56-65","65+"))))) -> 36-45 | R91: 1963 | S91: 11 | T91: 5 | U91: M | V91: USA | W91: California | X91: Investment | Y91: 4 | Z91: No | AA91: Website
B92: =C92*1000+G92 -> 3001 | C92: 3 | D92: 2007 | E92: 8 | F92: Apartment | G92: 1 | H92: 579.7488 | I92: 171262.65 | J92: Sold | L92: C0069 | M92: Individual | N92: Alonso | O92: Terrell | P92: =IF((D92-R92)=0," ",D92-R92) -> 44 | Q92: =IF(P92<26,"18-25",IF(P92<36,"26-35",IF(P92<46,"36-45",IF(P92<56,"46-55",IF(P92<66,"56-65","65+"))))) -> 36-45 | R92: 1963 | S92: 11 | T92: 5 | U92: M | V92: USA | W92: California | X92: Investment | Y92: 5 | Z92: No | AA92: Website
B93: =C93*1000+G93 -> 3043 | C93: 3 | D93: 2007 | E93: 11 | F93: Apartment | G93: 43 | H93: 1128.4012 | I93: 299159.14 | J93: Sold | L93: C0069 | M93: Individual | N93: Alonso | O93: Terrell | P93: =IF((D93-R93)=0," ",D93-R93) -> 44 | Q93: =IF(P93<26,"18-25",IF(P93<36,"26-35",IF(P93<46,"36-45",IF(P93<56,"46-55",IF(P93<66,"56-65","65+"))))) -> 36-45 | R93: 1963 | S93: 11 | T93: 5 | U93: M | V93: USA | W93: California | X93: Home | Y93: 5 | Z93: No | AA93: Website
B94: =C94*1000+G94 -> 2016 | C94: 2 | D94: 2007 | E94: 3 | F94: Apartment | G94: 16 | H94: 701.6596 | I94: 212265.67 | J94: Sold | L94: C0077 | M94: Individual | N94: Hazel | O94: Ayers | P94: =IF((D94-R94)=0," ",D94-R94) -> 44 | Q94: =IF(P94<26,"18-25",IF(P94<36,"26-35",IF(P94<46,"36-45",IF(P94<56,"46-55",IF(P94<66,"56-65","65+"))))) -> 36-45 | R94: 1963 | S94: 2 | T94: 1 | U94: M | V94: USA | W94: Colorado | X94: Home | Y94: 2 | Z94: No | AA94: Website
B95: =C95*1000+G95 -> 4049 | C95: 4 | D95: 2008 | E95: 1 | F95: Apartment | G95: 49 | H95: 1336.93 | I95: 388515.14 | J95: Sold | L95: C0168 | M95: Individual | N95: Brisa | O95: Mckee | P95: =IF((D95-R95)=0," ",D95-R95) -> 44 | Q95: =IF(P95<26,"18-25",IF(P95<36,"26-35",IF(P95<46,"36-45",IF(P95<56,"46-55",IF(P95<66,"56-65","65+"))))) -> 36-45 | R95: 1964 | S95: 9 | T95: 24 | U95: F | V95: USA | W95: California | X95: Home | Y95: 5 | Z95: No | AA95: Client
B96: =C96*1000+G96 -> 4022 | C96: 4 | D96: 2007 | E96: 8 | F96: Apartment | G96: 22 | H96: 794.5184 | I96: 263790.81 | J96: Sold | L96: C0058 | M96: Individual | N96: Johanna | O96: Fisher | P96: =IF((D96-R96)=0," ",D96-R96) -> 45 | Q96: =IF(P96<26,"18-25",IF(P96<36,"26-35",IF(P96<46,"36-45",IF(P96<56,"46-55",IF(P96<66,"56-65","65+"))))) -> 36-45 | R96: 1962 | S96: 8 | T96: 25 | U96: F | V96: USA | W96: California | X96: Home | Y96: 4 | Z96: Yes | AA96: Website
... B119: =C119*1000+G119 -> 3030 | C119: 3 | D119: 2006 | E119: 10 | F119: Apartment | G119: 30 | H119: 720.8124 | I119: 215774.28 | J119: Sold | L119: C0052 | M119: Individual | N119: Tristian | O119: Fuller | P119: =IF((D119-R119)=0," ",D119-R119) -> 50 | Q119: =IF(P119<26,"18-25",IF(P119<36,"26-35",IF(P119<46,"36-45",IF(P119<56,"46-55",IF(P119<66,"56-65","65+"))))) -> 46-55 | R119: 1956 | S119: 3 | T119: 13 | U119: M | V119: USA | W119: California | X119: Home | Y119: 5 | Z119: No | AA119: Agency
B120: =C120*1000+G120 -> 2003 | C120: 2 | D120: 2006 | E120: 12 | F120: Apartment | G120: 3 | H120: 927.0816 | I120: 289727.99 | J120: Sold | L120: C0063 | M120: Individual | N120: Piotr | O120: Aleksandrov | P120: =IF((D120-R120)=0," ",D120-R120) -> 51 | Q120: =IF(P120<26,"18-25",IF(P120<36,"26-35",IF(P120<46,"36-45",IF(P120<56,"46-55",IF(P120<66,"56-65","65+"))))) -> 46-55 | R120: 1955 | S120: 12 | T120: 2 | U120: M | V120: Russia | X120: Investment | Y120: 3 | Z120: No | AA120: Agency
B121: =C121*1000+G121 -> 5039 | C121: 5 | D121: 2008 | E121: 5 | F121: Apartment | G121: 39 | H121: 798.2844 | I121: 195874.94 | J121: Sold | L121: C0088 | M121: Individual | N121: Yurem | O121: Wright | P121: =IF((D121-R121)=0," ",D121-R121) -> 51 | Q121: =IF(P121<26,"18-25",IF(P121<36,"26-35",IF(P121<46,"36-45",IF(P121<56,"46-55",IF(P121<66,"56-65","65+"))))) -> 46-55 | R121: 1957 | S121: 3 | T121: 6 | U121: M | V121: USA | W121: California | X121: Home | Y121: 3 | Z121: Yes | AA121: Website
B122: =C122*1000+G122 -> 5030 | C122: 5 | D122: 2010 | E122: 5 | F122: Apartment | G122: 30 | H122: 1057.9232 | I122: 357538.2 | J122: Sold | L122: C0094 | M122: Individual | N122: Luis | O122: Crane | P122: =IF((D122-R122)=0," ",D122-R122) -> 51 | Q122: =IF(P122<26,"18-25",IF(P122<36,"26-35",IF(P122<46,"36-45",IF(P122<56,"46-55",IF(P122<66,"56-65","65+"))))) -> 46-55 | R122: 1959 | S122: 4 | T122: 20 | U122: M | V122: USA | W122: Nevada | X122: Home | Y122: 3 | Z122: Yes | AA122: Website
B123: =C123*1000+G123 -> 3041 | C123: 3 | D123: 2008 | E123: 1 | F123: Apartment | G123: 41 | H123: 781.0684 | I123: 239248.75 | J123: Sold | L123: C0165 | M123: Individual | N123: Anahi | O123: Curry | P123: =IF((D123-R123)=0," ",D123-R123) -> 51 | Q123: =IF(P123<26,"18-25",IF(P123<36,"26-35",IF(P123<46,"36-45",IF(P123<56,"46-55",IF(P123<66,"56-65","65+"))))) -> 46-55 | R123: 1957 | S123: 9 | T123: 9 | U123: M | V123: USA | W123: California | X123: Home | Y123: 5 | Z123: Yes | AA123: Client
B124: =C124*1000+G124 -> 2057 | C124: 2 | D124: 2006 | E124: 9 | F124: Apartment | G124: 57 | H124: 1396.8632 | I124: 382277.15 | J124: Sold | L124: C0044 | M124: Individual | N124: Ramiro | O124: Oneill | P124: =IF((D124-R124)=0," ",D124-R124) -> 52 | Q124: =IF(P124<26,"18-25",IF(P124<36,"26-35",IF(P124<46,"36-45",IF(P124<56,"46-55",IF(P124<66,"56-65","65+"))))) -> 46-55 | R124: 1954 | S124: 9 | T124: 29 | U124: M | V124: USA | W124: California | X124: Home | Y124: 4 | Z124: No | AA124: Agency
B125: =C125*1000+G125 -> 4028 | C125: 4 | D125: 2007 | E125: 2 | F125: Apartment | G125: 28 | H125: 794.5184 | I125: 248422.66 | J125: Sold | L125: C0157 | M125: Individual | N125: Erika | O125: Steward | P125: =IF((D125-R125)=0," ",D125-R125) -> 52 | Q125: =IF(P125<26,"18-25",IF(P125<36,"26-35",IF(P125<46,"36-45",IF(P125<56,"46-55",IF(P125<66,"56-65","65+"))))) -> 46-55 | R125: 1955 | S125: 8 | T125: 7 | U125: F | V125: USA | W125: California | X125: Investment | Y125: 4 | Z125: No | AA125: Website
B126: =C126*1000+G126 -> 3032 | C126: 3 | D126: 2007 | E126: 8 | F126: Apartment | G126: 32 | H126: 923.208 | I126: 242740.66 | J126: Sold | L126: C0118 | M126: Individual | N126: Dangelo | O126: Shea | P126: =IF((D126-R126)=0," ",D126-R126) -> 53 | Q126: =IF(P126<26,"18-25",IF(P126<36,"26-35",IF(P126<46,"36-45",IF(P126<56,"46-55",IF(P126<66,"56-65","65+"))))) -> 46-55 | R126: 1954 | S126: 2 | T126: 27 | U126: M | V126: Belgium | W126: Arizona | X126: Investment | Y126: 4 | Z126: No | AA126: Website
B127: =C127*1000+G127 -> 3013 | C127: 3 | D127: 2007 | E127: 8 | F127: Apartment | G127: 13 | H127: 781.0684 | I127: 253025.78 | J127: Sold | L127: C0119 | M127: Individual | N127: Miguel | O127: Walter | P127: =IF((D127-R127)=0," ",D127-R127) -> 53 | Q127: =IF(P127<26,"18-25",IF(P127<36,"26-35",IF(P127<46,"36-45",IF(P127<56,"46-55",IF(P127<66,"56-65","65+"))))) -> 46-55 | R127: 1954 | S127: 1 | T127: 7 | U127: M | V127: USA | W127: Arizona | X127: Home | Y127: 4 | Z127: No | AA127: Agency
B128: =C128*1000+G128 -> 1040 | C128: 1 | D128: 2006 | E128: 4 | F128: Apartment | G128: 40 | H128: 782.252 | I128: 234172.39 | J128: Sold | L128: C0033 | M128: Individual | N128: Alanna | O128: Hess | P128: =IF((D128-R128)=0," ",D128-R128) -> 54 | Q128: =IF(P128<26,"18-25",IF(P128<36,"26-35",IF(P128<46,"36-45",IF(P128<56,"46-55",IF(P128<66,"56-65","65+"))))) -> 46-55 | R128: 1952 | S128: 6 | T128: 19 | U128: F | V128: USA | W128: Nevada | X128: Home | Y128: 3 | Z128: No | AA128: Website
B129: =C129*1000+G129 -> 4031 | C129: 4 | D129: 2007 | E129: 6 | F129: Apartment | G129: 31 | H129: 733.1864 | I129: 200678.75 | J129: Sold | L129: C0100 | M129: Individual | N129: Simon | O129: Bennett | P129: =IF((D129-R129)=0," ",D129-R129) -> 54 | Q129: =IF(P129<26,"18-25",IF(P129<36,"26-35",IF(P129<46,"36-45",IF(P129<56,"46-55",IF(P129<66,"56-65","65+"))))) -> 46-55 | R129: 1953 | S129: 6 | T129: 9 | U129: M | V129: USA | W129: Colorado | X129: Home | Y129: 4 | Z129: No | AA129: Website
B130: =C130*1000+G130 -> 4019 | C130: 4 | D130: 2007 | E130: 12 | F130: Apartment | G130: 19 | H130: 733.1864 | I130: 226578.51 | J130: Sold | L130: C0133 | M130: Individual | N130: Ivan | O130: Bright | P130: =IF((D130-R130)=0," ",D130-R130) -> 54 | Q130: =IF(P130<26,"18-25",IF(P130<36,"26-35",IF(P130<46,"36-45",IF(P130<56,"46-55",IF(P130<66,"56-65","65+"))))) -> 46-55 | R130: 1953 | S130: 9 | T130: 15 | U130: M | V130: USA | W130: California | X130: Home | Y130: 4 | Z130: No | AA130: Website
B131: =C131*1000+G131 -> 4029 | C131: 4 | D131: 2007 | E131: 11 | F131: Apartment | G131: 29 | H131: 794.5184 | I131: 200148.89 | J131: Sold | L131: C0175 | M131: Individual | N131: Madeline | O131: Michael | P131: =IF((D131-R131)=0," ",D131-R131) -> 54 | Q131: =IF(P131<26,"18-25",IF(P131<36,"26-35",IF(P131<46,"36-45",IF(P131<56,"46-55",IF(P131<66,"56-65","65+"))))) -> 46-55 | R131: 1953 | S131: 7 | T131: 30 | U131: F | V131: USA | W131: California | X131: Home | Y131: 4 | Z131: Yes | AA131: Website
B132: =C132*1000+G132 -> 1021 | C132: 1 | D132: 2004 | E132: 10 | F132: Apartment | G132: 21 | H132: 756.2128 | I132: 218585.92 | J132: Sold | L132: C0008 | M132: Individual | N132: Arthur | O132: Bray | P132: =IF((D132-R132)=0," ",D132-R132) -> 55 | Q132: =IF(P132<26,"18-25",IF(P132<36,"26-35",IF(P132<46,"36-45",IF(P132<56,"46-55",IF(P132<66,"56-65","65+"))))) -> 46-55 | R132: 1949 | S132: 7 | T132: 14 | U132: M | V132: USA | W132: Utah | X132: Investment | Y132: 4 | Z132: No | AA132: Agency
... B144: =C144*1000+G144 -> 2030 | C144: 2 | D144: 2005 | E144: 12 | F144: Apartment | G144: 30 | H144: 723.8252 | I144: 214341.34 | J144: Sold | L144: C0031 | M144: Individual | N144: Cedric | O144: Goodwin | P144: =IF((D144-R144)=0," ",D144-R144) -> 57 | Q144: =IF(P144<26,"18-25",IF(P144<36,"26-35",IF(P144<46,"36-45",IF(P144<56,"46-55",IF(P144<66,"56-65","65+"))))) -> 56-65 | R144: 1948 | S144: 2 | T144: 20 | U144: M | V144: USA | W144: Utah | X144: Home | Y144: 4 | Z144: No | AA144: Client
B145: =C145*1000+G145 -> 3050 | C145: 3 | D145: 2006 | E145: 11 | F145: Apartment | G145: 50 | H145: 977.8688 | I145: 248274.31 | J145: Sold | L145: C0059 | M145: Individual | N145: Elena | O145: Petrova | P145: =IF((D145-R145)=0," ",D145-R145) -> 57 | Q145: =IF(P145<26,"18-25",IF(P145<36,"26-35",IF(P145<46,"36-45",IF(P145<56,"46-55",IF(P145<66,"56-65","65+"))))) -> 56-65 | R145: 1949 | S145: 6 | T145: 22 | U145: F | V145: Russia | X145: Home | Y145: 3 | Z145: Yes | AA145: Agency
B146: =C146*1000+G146 -> 5050 | C146: 5 | D146: 2007 | E146: 11 | F146: Apartment | G146: 50 | H146: 1093.0008 | I146: 390494.27 | J146: Sold | L146: C0140 | M146: Individual | N146: Aniya | O146: Miller | P146: =IF((D146-R146)=0," ",D146-R146) -> 57 | Q146: =IF(P146<26,"18-25",IF(P146<36,"26-35",IF(P146<46,"36-45",IF(P146<56,"46-55",IF(P146<66,"56-65","65+"))))) -> 56-65 | R146: 1950 | S146: 15 | T146: 2 | U146: F | V146: USA | W146: Nevada | X146: Home | Y146: 3 | Z146: No | AA146: Website
B147: =C147*1000+G147 -> 2039 | C147: 2 | D147: 2006 | E147: 8 | F147: Apartment | G147: 39 | H147: 927.8348 | I147: 293876.27 | J147: Sold | L147: C0043 | M147: Individual | N147: Kayley | O147: Nielsen | P147: =IF((D147-R147)=0," ",D147-R147) -> 59 | Q147: =IF(P147<26,"18-25",IF(P147<36,"26-35",IF(P147<46,"36-45",IF(P147<56,"46-55",IF(P147<66,"56-65","65+"))))) -> 56-65 | R147: 1947 | S147: 4 | T147: 27 | U147: F | V147: USA | W147: Arizona | X147: Home | Y147: 4 | Z147: Yes | AA147: Website
B148: =C148*1000+G148 -> 2008 | C148: 2 | D148: 2007 | E148: 3 | F148: Apartment | G148: 8 | H148: 701.6596 | I148: 204286.67 | J148: Sold | L148: C0078 | M148: Individual | N148: Zaiden | O148: Merritt | P148: =IF((D148-R148)=0," ",D148-R148) -> 59 | Q148: =IF(P148<26,"18-25",IF(P148<36,"26-35",IF(P148<46,"36-45",IF(P148<56,"46-55",IF(P148<66,"56-65","65+"))))) -> 56-65 | R148: 1948 | S148: 2 | T148: 23 | U148: M | V148: USA | W148: Wyoming | X148: Home | Y148: 3 | Z148: No | AA148: Agency
B149: =C149*1000+G149 -> 3019 | C149: 3 | D149: 2007 | E149: 9 | F149: Apartment | G149: 19 | H149: 680.57 | I149: 230154.53 | J149: Sold | L149: C0124 | M149: Individual | N149: Sonia | O149: Choi | P149: =IF((D149-R149)=0," ",D149-R149) -> 59 | Q149: =IF(P149<26,"18-25",IF(P149<36,"26-35",IF(P149<46,"36-45",IF(P149<56,"46-55",IF(P149<66,"56-65","65+"))))) -> 56-65 | R149: 1948 | S149: 11 | T149: 9 | U149: F | V149: USA | W149: Oregon | X149: Investment | Y149: 5 | Z149: No | AA149: Agency
B150: =C150*1000+G150 -> 2015 | C150: 2 | D150: 2006 | E150: 9 | F150: Apartment | G150: 15 | H150: 723.9328 | I150: 228170.03 | J150: Sold | L150: C0049 | M150: Individual | N150: Trey | O150: Strong | P150: =IF((D150-R150)=0," ",D150-R150) -> 48 | Q150: =IF(P150<26,"18-25",IF(P150<36,"26-35",IF(P150<46,"36-45",IF(P150<56,"46-55",IF(P150<66,"56-65","65+"))))) -> 46-55 | R150: 1958 | S150: 12 | T150: 20 | U150: M | V150: USA | W150: California | X150: Home | Y150: 4 | Z150: No | AA150: Agency
B151: =C151*1000+G151 -> 2033 | C151: 2 | D151: 2006 | E151: 9 | F151: Apartment | G151: 33 | H151: 649.7964 | I151: 205085.4 | J151: Sold | L151: C0049 | M151: Individual | N151: Trey | O151: Strong | P151: =IF((D151-R151)=0," ",D151-R151) -> 48 | Q151: =IF(P151<26,"18-25",IF(P151<36,"26-35",IF(P151<46,"36-45",IF(P151<56,"46-55",IF(P151<66,"56-65","65+"))))) -> 46-55 | R151: 1958 | S151: 12 | T151: 20 | U151: M | V151: USA | W151: California | X151: Home | Y151: 3 | Z151: No | AA151: Agency
B152: =C152*1000+G152 -> 2019 | C152: 2 | D152: 2007 | E152: 3 | F152: Apartment | G152: 19 | H152: 649.7964 | I152: 177555.06 | J152: Sold | L152: C0079 | M152: Individual | N152: Xavier | O152: Faulkner | P152: =IF((D152-R152)=0," ",D152-R152) -> 60 | Q152: =IF(P152<26,"18-25",IF(P152<36,"26-35",IF(P152<46,"36-45",IF(P152<56,"46-55",IF(P152<66,"56-65","65+"))))) -> 56-65 | R152: 1947 | S152: 5 | T152: 24 | U152: M | V152: Canada | X152: Investment | Y152: 5 | Z152: No | AA152: Website
B153: =C153*1000+G153 -> 2021 | C153: 2 | D153: 2007 | E153: 4 | F153: Apartment | G153: 21 | H153: 785.48 | I153: 217748.48 | J153: Sold | L153: C0079 | M153: Individual | N153: Xavier | O153: Faulkner | P153: =IF((D153-R153)=0," ",D153-R153) -> 60 | Q153: =IF(P153<26,"18-25",IF(P153<36,"26-35",IF(P153<46,"36-45",IF(P153<56,"46-55",IF(P153<66,"56-65","65+"))))) -> 56-65 | R153: 1947 | S153: 5 | T153: 24 | U153: M | V153: Canada | X153: Investment | Y153: 5 | Z153: No | AA153: Website
B154: =C154*1000+G154 -> 2027 | C154: 2 | D154: 2007 | E154: 4 | F154: Apartment | G154: 27 | H154: 785.48 | I154: 247739.44 | J154: Sold | L154: C0079 | M154: Individual | N154: Xavier | O154: Faulkner | P154: =IF((D154-R154)=0," ",D154-R154) -> 60 | Q154: =IF(P154<26,"18-25",IF(P154<36,"26-35",IF(P154<46,"36-45",IF(P154<56,"46-55",IF(P154<66,"56-65","65+"))))) -> 56-65 | R154: 1947 | S154: 5 | T154: 24 | U154: M | V154: Canada | X154: Investment | Y154: 5 | Z154: No | AA154: Website
B155: =C155*1000+G155 -> 2052 | C155: 2 | D155: 2007 | E155: 3 | F155: Apartment | G155: 52 | H155: 1615.2912 | I155: 484458.03 | J155: Sold | L155: C0079 | M155: Individual | N155: Xavier | O155: Faulkner | P155: =IF((D155-R155)=0," ",D155-R155) -> 60 | Q155: =IF(P155<26,"18-25",IF(P155<36,"26-35",IF(P155<46,"36-45",IF(P155<56,"46-55",IF(P155<66,"56-65","65+"))))) -> 56-65 | R155: 1947 | S155: 5 | T155: 24 | U155: M | V155: Canada | X155: Investment | Y155: 5 | Z155: No | AA155: Website
B156: =C156*1000+G156 -> 3006 | C156: 3 | D156: 2007 | E156: 2 | F156: Apartment | G156: 6 | H156: 1132.0596 | I156: 356506.37 | J156: Sold | L156: C0079 | M156: Individual | N156: Xavier | O156: Faulkner | P156: =IF((D156-R156)=0," ",D156-R156) -> 60 | Q156: =IF(P156<26,"18-25",IF(P156<36,"26-35",IF(P156<46,"36-45",IF(P156<56,"46-55",IF(P156<66,"56-65","65+"))))) -> 56-65 | R156: 1947 | S156: 5 | T156: 24 | U156: M | V156: Canada | X156: Investment | Y156: 5 | Z156: No | AA156: Website
B157: =C157*1000+G157 -> 3044 | C157: 3 | D157: 2007 | E157: 3 | F157: Apartment | G157: 44 | H157: 720.382 | I157: 197869.36 | J157: Sold | L157: C0079 | M157: Individual | N157: Xavier | O157: Faulkner | P157: =IF((D157-R157)=0," ",D157-R157) -> 60 | Q157: =IF(P157<26,"18-25",IF(P157<36,"26-35",IF(P157<46,"36-45",IF(P157<56,"46-55",IF(P157<66,"56-65","65+"))))) -> 56-65 | R157: 1947 | S157: 5 | T157: 24 | U157: M | V157: Canada | X157: Investment | Y157: 5 | Z157: No | AA157: Website
B158: =C158*1000+G158 -> 4025 | C158: 4 | D158: 2007 | E158: 12 | F158: Apartment | G158: 25 | H158: 733.1864 | I158: 236608.95 | J158: Sold | L158: C0079 | M158: Individual | N158: Xavier | O158: Faulkner | P158: =IF((D158-R158)=0," ",D158-R158) -> 60 | Q158: =IF(P158<26,"18-25",IF(P158<36,"26-35",IF(P158<46,"36-45",IF(P158<56,"46-55",IF(P158<66,"56-65","65+"))))) -> 56-65 | R158: 1947 | S158: 5 | T158: 24 | U158: M | V158: Canada | X158: Investment | Y158: 5 | Z158: No | AA158: Website
B159: =C159*1000+G159 -> 1015 | C159: 1 | D159: 2004 | E159: 11 | F159: Apartment | G159: 15 | H159: 782.252 | I159: 208930.81 | J159: Sold | L159: C0013 | M159: Individual | N159: Franklin | O159: Mack | P159: =IF((D159-R159)=0," ",D159-R159) -> 61 | Q159: =IF(P159<26,"18-25",IF(P159<36,"26-35",IF(P159<46,"36-45",IF(P159<56,"46-55",IF(P159<66,"56-65","65+"))))) -> 56-65 | R159: 1943 | S159: 6 | T159: 18 | U159: M | V159: USA | W159: Virginia | X159: Home | Y159: 5 | Z159: Yes | AA159: Website
B160: =C160*1000+G160 -> 5041 | C160: 5 | D160: 2007 | E160: 11 | F160: Apartment | G160: 41 | H160: 798.2844 | I160: 263123.42 | J160: Sold | L160: C0139 | M160: Individual | N160: Logan | O160: Simmons | P160: =IF((D160-R160)=0," ",D160-R160) -> 61 | Q160: =IF(P160<26,"18-25",IF(P160<36,"26-35",IF(P160<46,"36-45",IF(P160<56,"46-55",IF(P160<66,"56-65","65+"))))) -> 56-65 | R160: 1946 | S160: 9 | T160: 14 | U160: M | V160: USA | W160: California | X160: Investment | Y160: 4 | Z160: No | AA160: Agency
B161: =C161*1000+G161 -> 5036 | C161: 5 | D161: 2007 | E161: 11 | F161: Apartment | G161: 36 | H161: 1057.9232 | I161: 286433.57 | J161: Sold | L161: C0154 | M161: Individual | N161: Sidney | O161: Cline | P161: =IF((D161-R161)=0," ",D161-R161) -> 64 | Q161: =IF(P161<26,"18-25",IF(P161<36,"26-35",IF(P161<46,"36-45",IF(P161<56,"46-55",IF(P161<66,"56-65","65+"))))) -> 56-65 | R161: 1943 | S161: 7 | T161: 24 | U161: F | V161: USA | W161: California | X161: Home | Y161: 4 | Z161: Yes | AA161: Website
...

Sheet Task 1
B1: 365 DataScience RE California Database
B2: Types of data and levels of measurement
B4: Task 1: What are the types of data and the levels of measurement of the following variables: Cust ID, Mortgage, Year of sale
C7: Type of data | D7: Level of measurement
B8: Cust ID | C8: Numerical | D8: Ratio
B9: Mortgage | C9: Categorical | D9: Nominal
B10: Year of sale | C10: Categorical | D10: Ordinal
B13: Variable | C13: Type of data | D13: Level of measurement | E13: Comment
B14: Cust ID | C14: Categorical | D14: Nominal | E14: This variable has the same properties as ID.
B15: Mortgage | C15: Categorical | D15: Nominal | E15: This is a Binary variable. Like a Yes/No question or Gender.
B16: Year of sale | C16: Numerical, discrete | D16: Interval | E16: Year is a numerical variable. It is always discrete. The level of measurement is questionable, but we would treat it as interval, as the 0 year would be the time when the Big Bang happened. The current BC-AD calendar was arbitrary chosen (similarly to degrees Celsius and Fahrenheit).

Sheet Tasks 2,3,4
B1: 365 DataScience RE California Database
B2: Histograms. Graphing numerical data
B4: Task 2: Create a frequency distribution graph representing the price (that is a histogram with the highest possible number of bins - 267). Use data on all apartments and offices, no matter if sold or not.
B5: Task 3: Create a histogram which represents the Price variable. Choose interval width (bins) of length $100,000. If you don't know how to do that, refer to the Course notes on descriptive statistics provided with the first lecture in this section.
B6: Use the data on all properties, no matter if sold or not.
B7: Task 4: Interpret the results.
E43: Graph (2): Property prices are right skewed (meaning a few very expensive properties but the majority at around the $217K mark) | P43: Graph (1): Most of the property prices are concetrated around the $199k to $292K mark

Sheet Task 5
B1: 365 DataScience RE California Database
B2: Scatter plot. Plotting numerical data; establishing relationship between variables.
B4: Task 5: Create a scatter plot showing the relationship between Price and Area. Use the data on all properties, no matter if sold or not. Interpret the results.
D6: Output (price) should always be on they-axis
D36: There is a high correlation between the area and price

Sheet Tasks 6,7
B1: 365 DataScience RE California Database
B2: Frequency distribution table. Pareto diagram.
B4: Task 6: Create a frequency distribution table, where you list all the countries from which the company has buyers (country vs number of buyers). Count the absolute frequency, the relative frequency and the cumulative frequency.
B5: Task 7: Create a Pareto diagram representing the data.
C9: Country | D9: Absolute Frequency | E9: Relative Frequency | F9: Cumulative Frequency
C10: USA | D10: =COUNTIF('365RE'!$V$6:$V$201,'Tasks 6,7'!C10) -> 177 | E10: =D10/$D$18 -> 0.90769231 | F10: =E10 -> 0.90769231
C11: Canada | D11: =COUNTIF('365RE'!$V$6:$V$201,'Tasks 6,7'!C11) -> 7 | E11: =D11/$D$18 -> 0.035897436 | F11: =F10+E11 -> 0.94358974
C12: Russia | D12: =COUNTIF('365RE'!$V$6:$V$201,'Tasks 6,7'!C12) -> 4 | E12: =D12/$D$18 -> 0.020512821 | F12: =F11+E12 -> 0.96410256
C13: Belgium | D13: =COUNTIF('365RE'!$V$6:$V$201,'Tasks 6,7'!C13) -> 2 | E13: =D13/$D$18 -> 0.01025641 | F13: =F12+E13 -> 0.97435897
C14: UK | D14: =COUNTIF('365RE'!$V$6:$V$201,'Tasks 6,7'!C14) -> 2 | E14: =D14/$D$18 -> 0.01025641 | F14: =F13+E14 -> 0.98461538
C15: Denmark | D15: =COUNTIF('365RE'!$V$6:$V$201,'Tasks 6,7'!C15) -> 1 | E15: =D15/$D$18 -> 0.0051282051 | F15: =F14+E15 -> 0.98974359
C16: Germany | D16: =COUNTIF('365RE'!$V$6:$V$201,'Tasks 6,7'!C16) -> 1 | E16: =D16/$D$18 -> 0.0051282051 | F16: =F15+E16 -> 0.99487179
C17: Mexico | D17: =COUNTIF('365RE'!$V$6:$V$201,'Tasks 6,7'!C17) -> 1 | E17: =D17/$D$18 -> 0.0051282051 | F17: =F16+E17 -> 1
C18: Sum | D18: =SUM(D10:D17) -> 195 | E18: =SUM(E10:E17) -> 1

Sheet Tasks 8,9
B1: 365 DataScience RE California Database
B2: Measures of central tendency, asymmetry and variability
B4: Task 8: Calculate the mean, median, mode, skewness, variance and standard deviation of Price for all properties, no matter if sold or not.
B5: Task 9: Interpret the measures.
C7: Mean | D7: =AVERAGE('365RE'!I6:I272) -> 281171.9 | F7: The mean and the median are very cose together indicating that the dispersion of house prices are very close together
C8: Median | D8: =MEDIAN('365RE'!I6:I272) -> 249075.66 | F8: However, this is slighly skewed by the most frequently occuring value of $460K as demonstrated by the skewness factor
C9: Mode | D9: =_xlfn.MODE.SNGL('365RE'!I6:I272) -> 460001.26
C10: Skewness | D10: =SKEW('365RE'!I6:I272) -> 1.0960149 | F10: The variance shows a wide dispersion about the mean possibly by one outlier (expensive property) or the frequently occuring price
C11: Variance | D11: =_xlfn.VAR.P('365RE'!I6:I272) -> 7.9124716e+09
C12: Standard deviation | D12: =_xlfn.STDEV.P('365RE'!I6:I272) -> 88952.075

Sheet Task 10
B1: 365 DataScience RE California Database
B2: Measures of relationship between variables
B4: Task 10: Calculate the covariance and correlation coefficient between Price and Area, no matter if the property is sold or not. Is the result in line with the scatter plot?
B6: Covariance | C6: =_xlfn.COVARIANCE.P('365RE'!I6:I272,'365RE'!H6:H272) -> 24057281
B7: Corrolation | C7: =CORREL('365RE'!I6:I272,'365RE'!H6:H272) -> 0.95108738
B9: Corrolation aligns with the scatter plot
